{
  "title": "A Federated Learning Framework for Healthcare IoT devices",
  "authors": "Binhang Yuan, Song Ge, Wenhui Xing",
  "year": 2020,
  "url": "http://arxiv.org/abs/2005.05083v1",
  "abstract": "The Internet of Things (IoT) revolution has shown potential to give rise to\nmany medical applications with access to large volumes of healthcare data\ncollected by IoT devices. However, the increasing demand for healthcare data\nprivacy and security makes each IoT device an isolated island of data. Further,\nthe limited computation and communication capacity of wearable healthcare\ndevices restrict the application of vanilla federated learning. To this end, we\npropose an advanced federated learning framework to train deep neural networks,\nwhere the network is partitioned and allocated to IoT devices and a centralized\nserver. Then most of the training computation is handled by the powerful\nserver. The sparsification of activations and gradients significantly reduces\nthe communication overhead. Empirical study have suggested that the proposed\nframework guarantees a low accuracy loss, while only requiring 0.2% of the\nsynchronization traffic in vanilla federated learning.",
  "citation": 123
}