{
  "title": "Deep Mixed Effect Model using Gaussian Processes: A Personalized and\n  Reliable Prediction for Healthcare",
  "authors": "Ingyo Chung, Saehoon Kim, Juho Lee, Kwang Joon Kim, Sung Ju Hwang, Eunho Yang",
  "year": 2018,
  "url": "http://arxiv.org/abs/1806.01551v3",
  "abstract": "We present a personalized and reliable prediction model for healthcare, which\ncan provide individually tailored medical services such as diagnosis, disease\ntreatment, and prevention. Our proposed framework targets at making\npersonalized and reliable predictions from time-series data, such as Electronic\nHealth Records (EHR), by modeling two complementary components: i) a shared\ncomponent that captures global trend across diverse patients and ii) a\npatient-specific component that models idiosyncratic variability for each\npatient. To this end, we propose a composite model of a deep neural network to\nlearn complex global trends from the large number of patients, and Gaussian\nProcesses (GP) to probabilistically model individual time-series given\nrelatively small number of visits per patient. We evaluate our model on diverse\nand heterogeneous tasks from EHR datasets and show practical advantages over\nstandard time-series deep models such as pure Recurrent Neural Network (RNN).",
  "citation": 18
}