{
  "title": "Systolic blood pressure estimation using ECG and PPG in patients\n  undergoing surgery",
  "authors": "Shaoxiong Sun, Erik Bresch, Jens Muehlsteff, Lars Schmitt, Xi Long, Rick Bezemer, Igor Paulussen, Gerrit J. Noordergraaf, Ronald M. Aarts",
  "year": 2021,
  "url": "http://arxiv.org/abs/2112.12853v3",
  "abstract": "Background and Objectives: In a significant portion of surgeries, blood\npressure (BP) is often measured non-invasively in an intermittent manner. This\npractice has a risk of missing clinically relevant BP changes between two\nadjacent intermittent BP measurements. This study proposes a method to\nnon-invasively estimate systolic blood pressure (SBP) with high accuracy in\npatients undergoing surgery. Methods: Continuous arterial BP,\nelectrocardiography (ECG), and photoplethysmography (PPG) signals were acquired\nfrom 29 patients undergoing surgery. After extracting 9 features from the PPG\nand ECG signals, we dynamically selected features upon each intermittent\nmeasurement (every 10 min) of SBP based on feature robustness and the principle\nof correlation-based feature selection. Finally, multiple linear regression\nmodels were built to combine these features to estimate SBP every 30 s.\nResults: Compared to the reference SBP, the proposed method achieved a mean of\ndifference at 0.08 mmHg, a standard deviation of difference at 7.97 mmHg, and a\ncorrelation coefficient at 0.89 (p < 0.001). Conclusions: This study\ndemonstrates the feasibility of non-invasively estimating SBP every 30 s with\nhigh accuracy during surgery by using ECG, PPG, and intermittent SBP\nmeasurements every 10 min, which meets the standard of the Association for the\nAdvancement of Medical Instrumentation. The proposed method has the potential\nto enhance BP monitoring in the operating room, improving patient outcomes and\nexperiences.",
  "citation": 33
}